khan/__init__.py
khan/main.py
khan/mongodb_client.py
khan/commands/__init__.py
khan/commands/base.py
khan/commands/replication.py
khan/commands/top.py
khan/formatter/__init__.py
khan/formatter/table.py
khan/formatter/table_replication.py
khan/formatter/table_top.py
khan_mongo-0.1.9.dist-info/DESCRIPTION.rst
khan_mongo-0.1.9.dist-info/METADATA
khan_mongo-0.1.9.dist-info/RECORD
khan_mongo-0.1.9.dist-info/WHEEL
khan_mongo-0.1.9.dist-info/entry_points.txt
khan_mongo-0.1.9.dist-info/metadata.json
khan_mongo-0.1.9.dist-info/top_level.txt
